rldec/__init__.py
rldec/_version.py
rldec/callbacks.py
rldec/config.py
rldec/data_handler.py
rldec/decompose.py
rldec/features.py
rldec/loggers.py
rldec/logging.conf
rldec/model_handler.py
rldec/train_model.py
rldec/utils.py
rldec/agents/__init__.py
rldec/agents/dqntrainer.py
rldec/clients/__init__.py
rldec/clients/parsingClient.py
rldec/default_configs/default_config_CombSequential.json
rldec/default_configs/default_config_Flattened.json
rldec/default_configs/default_config_Sequential.json
rldec/environments/__init__.py
rldec/environments/decomp.py
rldec/environments/flattened.py
rldec/environments/flattened_seq.py
rldec/environments/sequential.py
rldec/metrics/__init__.py
rldec/metrics/coupling.py
rldec/metrics/granularity.py
rldec/metrics/modularity.py
rldec/metrics/utils.py
rldec/models/__init__.py
rldec/models/parse/__init__.py
rldec/models/parse/v1/__init__.py
rldec/models/parse/v1/parse_pb2.py
rldec/models/parse/v1/parse_pb2_grpc.py
rldec/models/parse/v2/__init__.py
rldec/models/parse/v2/parse_pb2.py
rldec/models/parse/v2/parse_pb2_grpc.py
rldec/models/rldec/__init__.py
rldec/models/rldec/v1/__init__.py
rldec/models/rldec/v1/rldec_pb2.py
rldec/models/rldec/v1/rldec_pb2_grpc.py
rldec-0.5.2.dist-info/LICENSE
rldec-0.5.2.dist-info/METADATA
rldec-0.5.2.dist-info/WHEEL
rldec-0.5.2.dist-info/top_level.txt
rldec-0.5.2.dist-info/RECORD
