Metadata-Version: 2.1
Name: rldec
Version: 0.5.2
Summary: RLDec is a decomposition tool that analyzes the source code of a monolithic Java application and suggests the recommended microservices for each class in the system using a Deep Reinforcement Learning based method.
Author: Khaled Sellami
License: Apache License
Project-URL: Repository, https://github.com/khaledsellami/decomp-rldec
Project-URL: Issues, https://github.com/khaledsellami/decomp-rldec/issues
Keywords: decomposition,monolith,microservices,automation,refactoring,reinforcement learning
Classifier: Programming Language :: Python
Classifier: Programming Language :: Python :: 3
Classifier: Topic :: Scientific/Engineering
Classifier: Intended Audience :: Developers
Requires-Python: >=3.10
License-File: LICENSE
Requires-Dist: numpy>=1.26.4
Requires-Dist: scipy>=1.11.4
Requires-Dist: pandas<=2.2.0,>=1.5.3
Requires-Dist: tifffile>=2024.1.30
Requires-Dist: protobuf<5.26.0rc1,>=4.25.2
Requires-Dist: networkx>=2.8.4
Requires-Dist: ray[rllib]>=2.9.2
Requires-Dist: scikit-learn>=1.2.2
Requires-Dist: gymnasium>=0.28.1
Requires-Dist: torch>=2.1.0
Requires-Dist: grpcio>=1.48.2
